conflictfree/__init__.py
conflictfree/grad_operator.py
conflictfree/length_model.py
conflictfree/loss_recorder.py
conflictfree/momentum_operator.py
conflictfree/utils.py
conflictfree/weight_model.py
conflictfree-0.1.8.dist-info/LICENSE
conflictfree-0.1.8.dist-info/METADATA
conflictfree-0.1.8.dist-info/WHEEL
conflictfree-0.1.8.dist-info/top_level.txt
conflictfree-0.1.8.dist-info/RECORD
