Metadata-Version: 2.1
Name: conflictfree
Version: 0.1.8
Summary: Official implementation of Conflict-free Inverse Gradients method
Home-page: https://tum-pbs.github.io/ConFIG/
Author: Qiang Liu, Mengyu Chu, Nils Thuerey
Author-email: qiangliu.7@outlook.com
Classifier: Programming Language :: Python :: 3
Classifier: License :: OSI Approved :: MIT License
Classifier: Operating System :: OS Independent
License-File: LICENSE
Requires-Dist: torch (>=1.9.0)
